src/__init__.py
src/main.py
refresh_my_ip-0.0.3.dist-info/LICENSE
refresh_my_ip-0.0.3.dist-info/METADATA
refresh_my_ip-0.0.3.dist-info/WHEEL
refresh_my_ip-0.0.3.dist-info/entry_points.txt
refresh_my_ip-0.0.3.dist-info/top_level.txt
refresh_my_ip-0.0.3.dist-info/RECORD
